enctempfile/__init__.py
enctempfile/impl.py
enctempfile-0.6.dist-info/LICENSE
enctempfile-0.6.dist-info/METADATA
enctempfile-0.6.dist-info/WHEEL
enctempfile-0.6.dist-info/top_level.txt
enctempfile-0.6.dist-info/RECORD
